pypbl/__init__.py
pypbl/elicitation.py
pypbl/priors.py
pypbl/samplers.py
pypbl-0.3.1.dist-info/LICENSE.md
pypbl-0.3.1.dist-info/WHEEL
pypbl-0.3.1.dist-info/METADATA
pypbl-0.3.1.dist-info/RECORD
