Metadata-Version: 2.1
Name: pypbl
Version: 0.3.1
Summary: A python library for preference based learning using pairwise comparisons.
Home-page: https://pypbl.readthedocs.io/en/latest/
License: MIT
Author: Jim Parr
Author-email: jimparr19@gmail.com
Requires-Python: >=3.7,<4.0
Classifier: License :: OSI Approved :: MIT License
Classifier: Programming Language :: Python :: 3
Classifier: Programming Language :: Python :: 3.7
Classifier: Programming Language :: Python :: 3.8
Requires-Dist: dunamai (>=1.0.0,<2.0.0)
Requires-Dist: emcee (>=3.0.2,<4.0.0)
Requires-Dist: numpy (>=1.18.0,<2.0.0)
Requires-Dist: pandas (>=0.25.3,<0.26.0)
Requires-Dist: scipy (>=1.4.1,<2.0.0)
Project-URL: Documentation, https://pypbl.readthedocs.io/en/stable/
Project-URL: Repository, https://github.com/jimparr19/pypbl
